.gitattributes
.gitignore
.gitlab-ci.yml
.readthedocs.yml
COPYING.md
FILESTRUCTURE.md
LICENSE.md
README.md
codecov.yml
pyproject.toml
setup.py
.github/dependabot.yml
.github/workflows/ci.yml
.github/workflows/draft-pdf.yml
.github/workflows/pypi.yml
astrolink/__init__.py
astrolink/_version.py
astrolink/astrolink.py
astrolink/io.py
astrolink/visualize.py
astrolink.egg-info/PKG-INFO
astrolink.egg-info/SOURCES.txt
astrolink.egg-info/dependency_links.txt
astrolink.egg-info/requires.txt
astrolink.egg-info/top_level.txt
data/Webb_Deep_Field.tif
data/newhalo_young.npy
doc/Makefile
doc/api.rst
doc/conf.py
doc/howitworks.md
doc/image_demo.nblink
doc/index.rst
doc/intro.rst
doc/make.bat
doc/simulated_galaxy_demo.nblink
images/howitworks/aggregation_process_with_probability_distribution.gif
images/howitworks/analogous_process_with_probability_distribution.gif
images/howitworks/data.png
images/howitworks/data_and_ordered_density_plot_with_final_clusters.png
images/howitworks/data_and_ordered_density_plot_with_some_clusters.png
images/howitworks/data_coloured_by_logrho.png
images/howitworks/data_with_clusters_from_analogy.png
images/howitworks/fitted_prominences.png
images/howitworks/probability_distribution_with_clusters.png
images/readme/AstroLink_logo_animated_dark.gif
images/readme/AstroLink_logo_animated_light.gif
images/readme/Estimated_Density_Field_Example.png
images/readme/Input_Data_with_Clusters.png
images/readme/Ordered_Density_Plot_Example.png
images/readme/Ordered_Density_Plot_with_Clusters.png
notebooks/image_demo.ipynb
notebooks/simulated_galaxy_demo.ipynb
paper/astrolink_example.png
paper/paper.bib
paper/paper.md
tests/__init__.py
tests/conftest.py
tests/test_astrolink.py
tests/test_io.py
tests/test_visualize.py