Metadata-Version: 2.4
Name: astrolink
Version: 0.5.3
Summary: A general-purpose algorithm for finding astrophysically-relevant clusters from point-cloud data.
Maintainer-email: William Oliver <william.hardie.oliver@gmail.com>
License: MIT
Classifier: Programming Language :: Python :: 3
Classifier: Operating System :: OS Independent
Classifier: License :: OSI Approved :: MIT License
Requires-Python: >=3.8
License-File: LICENSE.md
License-File: COPYING.md
Requires-Dist: numpy
Requires-Dist: numba
Requires-Dist: pykdtree
Requires-Dist: scipy
Requires-Dist: psutil
Requires-Dist: matplotlib
Provides-Extra: tests
Requires-Dist: pytest; extra == "tests"
Requires-Dist: pytest-cov; extra == "tests"
Requires-Dist: nbval; extra == "tests"
Provides-Extra: docs
Requires-Dist: ipykernel; extra == "docs"
Requires-Dist: nbsphinx; extra == "docs"
Requires-Dist: nbsphinx-link; extra == "docs"
Requires-Dist: sphinx; extra == "docs"
Requires-Dist: sphinx_mdinclude; extra == "docs"
Requires-Dist: sphinx_rtd_theme; extra == "docs"
Dynamic: license-file
